{
	"format_version": "1.9.0",
	"credit": "Made with Blockbench",
	"texture_size": [32, 32],
	"textures": {
		"2": "block/cactus2",
		"particle": "block/cactus2"
	},
	"elements": [
		{
			"from": [9.86, -0.3, -0.835],
			"to": [14.51, 9.58125, 3.815],
			"rotation": {"angle": 0, "axis": "y", "origin": [14.51, -0.3, 3.815]},
			"faces": {
				"north": {"uv": [5.5, 6.5, 6.5, 9], "texture": "#2"},
				"east": {"uv": [6.5, 6.5, 7.5, 9], "texture": "#2"},
				"south": {"uv": [2.5, 5.5, 3.5, 8], "texture": "#2"},
				"west": {"uv": [6, 1.5, 7, 4], "texture": "#2"},
				"up": {"uv": [11.5, 2.5, 10.5, 1.5], "rotation": 180, "texture": "#2"},
				"down": {"uv": [11.5, 2.5, 10.5, 3.5], "rotation": 180, "texture": "#2"}
			}
		},
		{
			"from": [9.86, 6.32625, 1.2575],
			"to": [14.51, 14.46375, 4.62875],
			"rotation": {"angle": 45, "axis": "x", "origin": [14.51, 6.32625, 4.62875]},
			"faces": {
				"north": {"uv": [4.5, 4.5, 5.5, 7.5], "texture": "#2"},
				"east": {"uv": [5, 1.5, 6, 4.5], "texture": "#2"},
				"south": {"uv": [4, 1.5, 5, 4.5], "texture": "#2"},
				"west": {"uv": [3.5, 4.5, 4.5, 7.5], "texture": "#2"},
				"up": {"uv": [11.5, 4.5, 10.5, 3.5], "rotation": 180, "texture": "#2"},
				"down": {"uv": [11.5, 4.5, 10.5, 5.5], "rotation": 180, "texture": "#2"}
			}
		},
		{
			"from": [9.86, 18.3, 5.55875],
			"to": [14.51, 24.1125, 8.465],
			"rotation": {"angle": 22.5, "axis": "x", "origin": [14.51, 18.3, 8.465]},
			"faces": {
				"north": {"uv": [8.5, 0, 9.5, 2], "texture": "#2"},
				"east": {"uv": [8.5, 2, 9.5, 4], "texture": "#2"},
				"south": {"uv": [0, 8, 1, 10], "texture": "#2"},
				"west": {"uv": [2.5, 8, 3.5, 10], "texture": "#2"},
				"up": {"uv": [10.5, 11.5, 9.5, 10.5], "rotation": 180, "texture": "#2"},
				"down": {"uv": [11.5, 10.5, 10.5, 11.5], "rotation": 180, "texture": "#2"}
			}
		},
		{
			"from": [9.86, 20.625, 3.815],
			"to": [14.51, 27.6, 7.7675],
			"rotation": {"angle": -45, "axis": "x", "origin": [14.51, 20.625, 6.14]},
			"faces": {
				"north": {"uv": [5.5, 9, 6.5, 11], "texture": "#2"},
				"east": {"uv": [7, 2, 8.25, 4], "texture": "#2"},
				"south": {"uv": [8.5, 4, 9.5, 6], "texture": "#2"},
				"west": {"uv": [7, 0, 8.25, 2], "texture": "#2"},
				"up": {"uv": [5, 11.25, 4, 10], "rotation": 180, "texture": "#2"},
				"down": {"uv": [11, 6, 10, 7.25], "rotation": 180, "texture": "#2"}
			}
		},
		{
			"from": [9.74375, 25.275, -0.835],
			"to": [14.62625, 29.925, 3.1175],
			"rotation": {"angle": -22.5, "axis": "x", "origin": [14.51, 25.275, 1.49]},
			"faces": {
				"north": {"uv": [6.5, 9, 7.5, 11], "texture": "#2"},
				"east": {"uv": [1, 7.5, 2.25, 9.5], "texture": "#2"},
				"south": {"uv": [9, 6, 10, 8], "texture": "#2"},
				"west": {"uv": [7, 4, 8.25, 6], "texture": "#2"},
				"up": {"uv": [11, 8.75, 10, 7.5], "rotation": 180, "texture": "#2"},
				"down": {"uv": [9.5, 10, 8.5, 11.25], "rotation": 180, "texture": "#2"}
			}
		},
		{
			"from": [9.86, 23.76375, 6.72125],
			"to": [14.51, 29.57625, 10.20875],
			"rotation": {"angle": -22.5, "axis": "x", "origin": [14.51, 23.76375, 9.04625]},
			"faces": {
				"north": {"uv": [9, 8, 10, 10], "texture": "#2"},
				"east": {"uv": [5.5, 4.5, 7, 6.5], "texture": "#2"},
				"south": {"uv": [7.5, 9, 8.5, 11], "texture": "#2"},
				"west": {"uv": [1, 5.5, 2.5, 7.5], "texture": "#2"},
				"up": {"uv": [10.5, 3, 9.5, 1.5], "rotation": 180, "texture": "#2"},
				"down": {"uv": [10.5, 3, 9.5, 4.5], "rotation": 180, "texture": "#2"}
			}
		},
		{
			"from": [9.86, 5.0475, 5.55875],
			"to": [14.51, 7.8375, 13.69625],
			"rotation": {"angle": -22.5, "axis": "x", "origin": [14.51, 5.5125, 5.55875]},
			"faces": {
				"north": {"uv": [10.5, 0, 11.5, 1.25], "texture": "#2"},
				"east": {"uv": [1, 4, 3.5, 5.25], "texture": "#2"},
				"south": {"uv": [10, 9, 11, 10.25], "texture": "#2"},
				"west": {"uv": [4, 0, 6.5, 1.25], "texture": "#2"},
				"up": {"uv": [4.5, 10, 3.5, 7.5], "rotation": 180, "texture": "#2"},
				"down": {"uv": [5.5, 7.5, 4.5, 10], "rotation": 180, "texture": "#2"}
			}
		},
		{
			"from": [9.74375, 9.93, 2.76875],
			"to": [14.62625, 21.555, 7.41875],
			"rotation": {"angle": 0, "axis": "y", "origin": [14.51, 21.555, 8.58125]},
			"faces": {
				"north": {"uv": [0, 4, 1, 8], "texture": "#2"},
				"east": {"uv": [1.5, 0, 3, 4], "texture": "#2"},
				"south": {"uv": [3, 0, 4, 4], "texture": "#2"},
				"west": {"uv": [0, 0, 1.5, 4], "texture": "#2"},
				"up": {"uv": [10.5, 1.5, 9.5, 0], "rotation": 180, "texture": "#2"},
				"down": {"uv": [2, 9.5, 1, 11], "rotation": 180, "texture": "#2"}
			}
		},
		{
			"from": [9.86, 9, -0.835],
			"to": [14.51, 14.8125, 2.6525],
			"rotation": {"angle": -22.5, "axis": "x", "origin": [14.51, 9, 1.49]},
			"faces": {
				"north": {"uv": [0, 10, 1, 11.5], "texture": "#2"},
				"east": {"uv": [7.5, 7.5, 9, 9], "texture": "#2"},
				"south": {"uv": [9.5, 4.5, 10.5, 6], "texture": "#2"},
				"west": {"uv": [7.5, 6, 9, 7.5], "texture": "#2"},
				"up": {"uv": [3, 11.5, 2, 10], "rotation": 180, "texture": "#2"},
				"down": {"uv": [4, 10, 3, 11.5], "rotation": 180, "texture": "#2"}
			}
		},
		{
			"from": [11.255, 11.5575, -4.43875],
			"to": [13.115, 13.8825, -2.11375],
			"rotation": {"angle": 22.5, "axis": "x", "origin": [13.3475, 13.8825, -2.11375]},
			"faces": {
				"north": {"uv": [1, 11, 1.75, 12], "texture": "#2"},
				"east": {"uv": [1, 11, 1.75, 12], "texture": "#2"},
				"south": {"uv": [1, 11, 1.75, 12], "texture": "#2"},
				"west": {"uv": [1, 11, 1.75, 12], "texture": "#2"},
				"up": {"uv": [1, 11, 1.75, 12], "rotation": 180, "texture": "#2"},
				"down": {"uv": [1, 11, 1.75, 12], "rotation": 180, "texture": "#2"}
			}
		},
		{
			"from": [11.255, 14.58, -1.9975],
			"to": [13.115, 16.905, 0.3275],
			"rotation": {"angle": -22.5, "axis": "x", "origin": [13.3475, 14.58, 0.3275]},
			"faces": {
				"north": {"uv": [1, 11, 1.75, 12], "texture": "#2"},
				"east": {"uv": [1, 11, 1.75, 12], "texture": "#2"},
				"south": {"uv": [1, 11, 1.75, 12], "texture": "#2"},
				"west": {"uv": [1, 11, 1.75, 12], "texture": "#2"},
				"up": {"uv": [1, 11, 1.75, 12], "rotation": 180, "texture": "#2"},
				"down": {"uv": [1, 11, 1.75, 12], "rotation": 180, "texture": "#2"}
			}
		},
		{
			"from": [11.255, 13.53375, -0.6025],
			"to": [13.115, 15.85875, 1.7225],
			"rotation": {"angle": 22.5, "axis": "x", "origin": [13.3475, 13.53375, 1.7225]},
			"faces": {
				"north": {"uv": [1, 11, 1.75, 12], "texture": "#2"},
				"east": {"uv": [1, 11, 1.75, 12], "texture": "#2"},
				"south": {"uv": [1, 11, 1.75, 12], "texture": "#2"},
				"west": {"uv": [1, 11, 1.75, 12], "texture": "#2"},
				"up": {"uv": [1, 11, 1.75, 12], "rotation": 180, "texture": "#2"},
				"down": {"uv": [1, 11, 1.75, 12], "rotation": 180, "texture": "#2"}
			}
		},
		{
			"from": [11.255, 29.11125, -2.9275],
			"to": [13.115, 31.32, -0.6025],
			"rotation": {"angle": -45, "axis": "x", "origin": [13.3475, 29.11125, -0.6025]},
			"faces": {
				"north": {"uv": [1, 11, 1.75, 12], "texture": "#2"},
				"east": {"uv": [1, 11, 1.75, 12], "texture": "#2"},
				"south": {"uv": [1, 11, 1.75, 12], "texture": "#2"},
				"west": {"uv": [1, 11, 1.75, 12], "texture": "#2"},
				"up": {"uv": [1, 11, 1.75, 12], "rotation": 180, "texture": "#2"},
				"down": {"uv": [1, 11, 1.75, 12], "rotation": 180, "texture": "#2"}
			}
		},
		{
			"from": [11.255, 28.87875, -0.6025],
			"to": [13.115, 31.20375, 1.7225],
			"rotation": {"angle": 22.5, "axis": "x", "origin": [13.3475, 28.87875, 1.7225]},
			"faces": {
				"north": {"uv": [1, 11, 1.75, 12], "texture": "#2"},
				"east": {"uv": [1, 11, 1.75, 12], "texture": "#2"},
				"south": {"uv": [1, 11, 1.75, 12], "texture": "#2"},
				"west": {"uv": [1, 11, 1.75, 12], "texture": "#2"},
				"up": {"uv": [1, 11, 1.75, 12], "rotation": 180, "texture": "#2"},
				"down": {"uv": [1, 11, 1.75, 12], "rotation": 180, "texture": "#2"}
			}
		},
		{
			"from": [11.255, 9.2325, 10.44125],
			"to": [13.115, 11.5575, 12.76625],
			"rotation": {"angle": 22.5, "axis": "x", "origin": [13.3475, 9.2325, 12.76625]},
			"faces": {
				"north": {"uv": [1, 11, 1.75, 12], "texture": "#2"},
				"east": {"uv": [1, 11, 1.75, 12], "texture": "#2"},
				"south": {"uv": [1, 11, 1.75, 12], "texture": "#2"},
				"west": {"uv": [1, 11, 1.75, 12], "texture": "#2"},
				"up": {"uv": [1, 11, 1.75, 12], "rotation": 180, "texture": "#2"},
				"down": {"uv": [1, 11, 1.75, 12], "rotation": 180, "texture": "#2"}
			}
		},
		{
			"from": [11.255, 6.9075, 12.65],
			"to": [13.115, 9.2325, 14.975],
			"rotation": {"angle": -22.5, "axis": "x", "origin": [13.3475, 6.9075, 12.65]},
			"faces": {
				"north": {"uv": [1, 11, 1.75, 12], "texture": "#2"},
				"east": {"uv": [1, 11, 1.75, 12], "texture": "#2"},
				"south": {"uv": [1, 11, 1.75, 12], "texture": "#2"},
				"west": {"uv": [1, 11, 1.75, 12], "texture": "#2"},
				"up": {"uv": [1, 11, 1.75, 12], "rotation": 180, "texture": "#2"},
				"down": {"uv": [1, 11, 1.75, 12], "rotation": 180, "texture": "#2"}
			}
		},
		{
			"from": [11.255, 22.13625, 10.325],
			"to": [13.115, 24.46125, 12.65],
			"rotation": {"angle": -22.5, "axis": "x", "origin": [13.3475, 22.13625, 10.325]},
			"faces": {
				"north": {"uv": [1, 11, 1.75, 12], "texture": "#2"},
				"east": {"uv": [1, 11, 1.75, 12], "texture": "#2"},
				"south": {"uv": [1, 11, 1.75, 12], "texture": "#2"},
				"west": {"uv": [1, 11, 1.75, 12], "texture": "#2"},
				"up": {"uv": [1, 11, 1.75, 12], "rotation": 180, "texture": "#2"},
				"down": {"uv": [1, 11, 1.75, 12], "rotation": 180, "texture": "#2"}
			}
		}
	],
	"groups": [
		{
			"name": "group",
			"origin": [8, 8, 8],
			"color": 0,
			"children": [0, 1, 2, 3, 4, 5, 6, 7, 8, 9, 10, 11, 12, 13, 14, 15, 16]
		}
	]
}